{"type":"FeatureCollection","features":[{"id":"C94AE36F-0F09-4D5D-A219-D2D66A28E4A2","type":"Feature","properties":{"portNumber":55680,"portName":"Pago Pago Harbor","regionNumber":55675,"regionName":"AMERICAN SAMOA","countryCode":"AS","countryName":"American Samoa","latitude":"14°17'00\"S","longitude":"170°40'00\"W","publicationNumber":"U.S. Coast Pilot 10 - Oregon Washington Hawaii and Pacific Islands","chartNumber":"83484","navArea":"XIV","harborSize":"S","harborType":"CN","shelter":"G","erTide":"N","erSwell":"Y","erIce":"N","erOther":"N","overheadLimits":"N","chDepth":"23","anDepth":"11","cpDepth":"16","otDepth":"11","tide":3,"maxVesselLength":null,"maxVesselBeam":null,"maxVesselDraft":null,"goodHoldingGround":"Y","turningArea":"Y","firstPortOfEntry":"Y","usRep":"Y","ptCompulsory":"N","ptAvailable":null,"ptLocalAssist":null,"ptAdvisable":"Y","tugsSalvage":"U","tugsAssist":"Y","qtPratique":"Y","qtOther":"U","cmTelephone":"Y","cmTelegraph":"U","cmRadio":"Y","cmRadioTel":"U","cmAir":"Y","cmRail":"U","loWharves":"Y","loAnchor":"U","loMedMoor":"U","loBeachMoor":"U","loIceMoor":"U","medFacilities":"U","garbageDisposal":"Y","degauss":"U","dirtyBallast":"Y","crFixed":"U","crMobile":"U","crFloating":"Y","lifts100":"U","lifts50":"U","lifts25":"U","lifts0":"Y","srLongshore":"Y","srElectrical":"U","srSteam":"U","srNavigEquip":"U","srElectRepair":"U","suProvisions":"U","suWater":"Y","suFuel":"Y","suDiesel":"Y","suDeck":"U","suEngine":"U","repairCode":"C","drydock":"U","railway":"S","qtSanitation":"U","suAviationFuel":"U","harborUse":"UNK","ukcMgmtSystem":"U","portSecurity":"U","etaMessage":"Y","searchAndRescue":"U","tss":"U","vts":"U","cht":"U","globalId":"{C94AE36F-0F09-4D5D-A219-D2D66A28E4A2}","loRoro":"U","loSolidBulk":"U","loContainer":"U","loBreakBulk":"U","loOilTerm":"U","loLongTerm":"U","loOther":"U","loDangCargo":"U","loLiquidBulk":"U","srIceBreaking":"U","srDiving":"U","cranesContainer":"U","unloCode":"AS PPG","dnc":"a0655660, gen06c, h0655680","s121WaterBody":"","s57Enc":null,"s101Enc":"","dodWaterBody":"South Pacific Ocean","alternateName":null,"entranceWidth":null,"lngTerminalDepth":null,"offMaxVesselLength":null,"offMaxVesselBeam":null,"offMaxVesselDraft":null,"ycoord":-14.28333299999997,"xcoord":-170.66666699999996},"geometry":{"type":"Point","coordinates":[-170.666667,-14.283333]}}]}