{"type":"FeatureCollection","features":[{"id":"7B717D8E-552B-4CB4-AE38-D72B79B25490","type":"Feature","properties":{"portNumber":11830,"portName":"Sint Nicolaas Baai","regionNumber":11825,"regionName":"ARUBA","countryCode":"AW","countryName":"Aruba","latitude":"12°26'00\"N","longitude":"69°55'00\"W","publicationNumber":"Sailing Directions Pub. 148 (Enroute) - Caribbean Sea - Volume II","chartNumber":"24463","navArea":"IV","harborSize":"S","harborType":"CB","shelter":"F","erTide":"N","erSwell":"N","erIce":"N","erOther":"Y","overheadLimits":"U","chDepth":"13","anDepth":"23","cpDepth":"13","otDepth":"23","tide":2,"maxVesselLength":null,"maxVesselBeam":null,"maxVesselDraft":null,"goodHoldingGround":"U","turningArea":"Y","firstPortOfEntry":"Y","usRep":"Y","ptCompulsory":"Y","ptAvailable":null,"ptLocalAssist":null,"ptAdvisable":"Y","tugsSalvage":"U","tugsAssist":"Y","qtPratique":"U","qtOther":"Y","cmTelephone":"U","cmTelegraph":"U","cmRadio":"Y","cmRadioTel":"U","cmAir":"Y","cmRail":"U","loWharves":"Y","loAnchor":"U","loMedMoor":"Y","loBeachMoor":"U","loIceMoor":"U","medFacilities":"Y","garbageDisposal":"U","degauss":"U","dirtyBallast":"Y","crFixed":"U","crMobile":"U","crFloating":"U","lifts100":"U","lifts50":"U","lifts25":"U","lifts0":"U","srLongshore":"Y","srElectrical":"Y","srSteam":"Y","srNavigEquip":"Y","srElectRepair":"Y","suProvisions":"Y","suWater":"Y","suFuel":"Y","suDiesel":"Y","suDeck":"Y","suEngine":"Y","repairCode":"C","drydock":"U","railway":"S","qtSanitation":"U","suAviationFuel":"U","harborUse":"UNK","ukcMgmtSystem":"U","portSecurity":"U","etaMessage":"Y","searchAndRescue":"U","tss":"U","vts":"U","cht":"U","globalId":"{7B717D8E-552B-4CB4-AE38-D72B79B25490}","loRoro":"U","loSolidBulk":"U","loContainer":"U","loBreakBulk":"U","loOilTerm":"U","loLongTerm":"U","loOther":"U","loDangCargo":"U","loLiquidBulk":"U","srIceBreaking":"U","srDiving":"U","cranesContainer":"U","unloCode":"AW SNL","dnc":"a1411825, coa14k, gen14a, h1411830","s121WaterBody":"","s57Enc":null,"s101Enc":"","dodWaterBody":"Caribbean Sea; North Atlantic Ocean","alternateName":"Sint Nicolaashaven; St Nicolass","entranceWidth":null,"lngTerminalDepth":null,"offMaxVesselLength":null,"offMaxVesselBeam":null,"offMaxVesselDraft":null,"ycoord":12.433333000000061,"xcoord":-69.91666699999996},"geometry":{"type":"Point","coordinates":[-69.916667,12.433333]}}]}