{"type":"FeatureCollection","features":[{"id":"92A07D55-F392-4808-917E-9916516B2207","type":"Feature","properties":{"portNumber":46286,"portName":"Moudi Marine Terminal","regionNumber":46250,"regionName":"CAMEROON","countryCode":"CM","countryName":"Cameroon","latitude":"4°07'00\"N","longitude":"8°29'00\"E","publicationNumber":"Sailing Directions Pub. 123 (Enroute) - Southwest Coast of Africa","chartNumber":"57165","navArea":"II","harborSize":"V","harborType":"OR","shelter":"P","erTide":"U","erSwell":"U","erIce":"U","erOther":"Y","overheadLimits":"Y","chDepth":null,"anDepth":"23","cpDepth":null,"otDepth":"23","tide":3,"maxVesselLength":null,"maxVesselBeam":null,"maxVesselDraft":null,"goodHoldingGround":"U","turningArea":"U","firstPortOfEntry":"Y","usRep":"Y","ptCompulsory":"Y","ptAvailable":null,"ptLocalAssist":null,"ptAdvisable":"Y","tugsSalvage":"U","tugsAssist":"Y","qtPratique":"U","qtOther":"Y","cmTelephone":"U","cmTelegraph":"U","cmRadio":"Y","cmRadioTel":"U","cmAir":"Y","cmRail":"U","loWharves":"U","loAnchor":"Y","loMedMoor":"Y","loBeachMoor":"U","loIceMoor":"U","medFacilities":"U","garbageDisposal":"U","degauss":"U","dirtyBallast":"N","crFixed":"Y","crMobile":"U","crFloating":"U","lifts100":"U","lifts50":"U","lifts25":"U","lifts0":"Y","srLongshore":"U","srElectrical":"U","srSteam":"U","srNavigEquip":"U","srElectRepair":"U","suProvisions":"N","suWater":"N","suFuel":"N","suDiesel":"U","suDeck":"U","suEngine":"U","repairCode":"N","drydock":"U","railway":"U","qtSanitation":"Y","suAviationFuel":"U","harborUse":"UNK","ukcMgmtSystem":"U","portSecurity":"U","etaMessage":"Y","searchAndRescue":"U","tss":"U","vts":"U","cht":"U","globalId":"{92A07D55-F392-4808-917E-9916516B2207}","loRoro":"U","loSolidBulk":"U","loContainer":"U","loBreakBulk":"U","loOilTerm":"U","loLongTerm":"U","loOther":"U","loDangCargo":"U","loLiquidBulk":"U","srIceBreaking":"U","srDiving":"U","cranesContainer":"U","unloCode":"CM MOU","dnc":"coa01a, gen01b","s121WaterBody":"","s57Enc":null,"s101Enc":"","dodWaterBody":"Gulf of Guinea; North Atlantic Ocean","alternateName":null,"entranceWidth":null,"lngTerminalDepth":null,"offMaxVesselLength":null,"offMaxVesselBeam":null,"offMaxVesselDraft":null,"ycoord":4.116667000000064,"xcoord":8.483333000000073},"geometry":{"type":"Point","coordinates":[8.483333,4.116667]}}]}