{"type":"FeatureCollection","features":[{"id":"35B58D3C-1DA8-4699-A1B9-961C19CBA2F5","type":"Feature","properties":{"portNumber":45825,"portName":"Banjul","regionNumber":45824,"regionName":"GAMBIA","countryCode":"GM","countryName":"Gambia, The","latitude":"13°27'00\"N","longitude":"16°34'00\"W","publicationNumber":"Sailing Directions Pub. 143 (Enroute) - West Coast of Europe and Northwest Africa","chartNumber":"51562","navArea":"II","harborSize":"V","harborType":"RN","shelter":"F","erTide":"Y","erSwell":"N","erIce":"N","erOther":"Y","overheadLimits":"N","chDepth":"8","anDepth":"14","cpDepth":"9","otDepth":"5","tide":2,"maxVesselLength":null,"maxVesselBeam":null,"maxVesselDraft":null,"goodHoldingGround":"Y","turningArea":"Y","firstPortOfEntry":"Y","usRep":"Y","ptCompulsory":"Y","ptAvailable":null,"ptLocalAssist":null,"ptAdvisable":"U","tugsSalvage":"U","tugsAssist":"Y","qtPratique":"Y","qtOther":"Y","cmTelephone":"Y","cmTelegraph":"U","cmRadio":"Y","cmRadioTel":"Y","cmAir":"Y","cmRail":"U","loWharves":"Y","loAnchor":"Y","loMedMoor":"Y","loBeachMoor":"U","loIceMoor":"U","medFacilities":"Y","garbageDisposal":"Y","degauss":"U","dirtyBallast":"Y","crFixed":"U","crMobile":"Y","crFloating":"U","lifts100":"U","lifts50":"U","lifts25":"U","lifts0":"Y","srLongshore":"Y","srElectrical":"Y","srSteam":"U","srNavigEquip":"U","srElectRepair":"U","suProvisions":"Y","suWater":"Y","suFuel":"Y","suDiesel":"N","suDeck":"Y","suEngine":"Y","repairCode":"C","drydock":"U","railway":"U","qtSanitation":"Y","suAviationFuel":"U","harborUse":"UNK","ukcMgmtSystem":"U","portSecurity":"U","etaMessage":"Y","searchAndRescue":"U","tss":"U","vts":"U","cht":"U","globalId":"{35B58D3C-1DA8-4699-A1B9-961C19CBA2F5}","loRoro":"U","loSolidBulk":"U","loContainer":"U","loBreakBulk":"U","loOilTerm":"U","loLongTerm":"U","loOther":"U","loDangCargo":"U","loLiquidBulk":"U","srIceBreaking":"U","srDiving":"U","cranesContainer":"U","unloCode":"GM BJL","dnc":"a0145825, coa01b, gen01a, h0145825","s121WaterBody":"","s57Enc":null,"s101Enc":"","dodWaterBody":"North Atlantic Ocean","alternateName":"Bathurst","entranceWidth":null,"lngTerminalDepth":null,"offMaxVesselLength":null,"offMaxVesselBeam":null,"offMaxVesselDraft":null,"ycoord":13.450000000000045,"xcoord":-16.56666699999994},"geometry":{"type":"Point","coordinates":[-16.566667,13.45]}}]}