{"type":"FeatureCollection","features":[{"id":"BA64EA55-5E40-48E9-814A-15BD8EE4E641","type":"Feature","properties":{"portNumber":39025,"portName":"Monaco","regionNumber":39020,"regionName":"MONACO","countryCode":"MC","countryName":"Monaco","latitude":"43°44'00\"N","longitude":"7°25'00\"E","publicationNumber":"Sailing Directions Pub. 131 (Enroute) - Western Mediterranean","chartNumber":"53093","navArea":"III","harborSize":"V","harborType":"CB","shelter":"G","erTide":"N","erSwell":"N","erIce":"N","erOther":"Y","overheadLimits":"Y","chDepth":"8","anDepth":"23","cpDepth":"11","otDepth":null,"tide":0,"maxVesselLength":null,"maxVesselBeam":null,"maxVesselDraft":null,"goodHoldingGround":"Y","turningArea":"U","firstPortOfEntry":"Y","usRep":"Y","ptCompulsory":"Y","ptAvailable":null,"ptLocalAssist":null,"ptAdvisable":"Y","tugsSalvage":"U","tugsAssist":"Y","qtPratique":"U","qtOther":"U","cmTelephone":"Y","cmTelegraph":"Y","cmRadio":"Y","cmRadioTel":"U","cmAir":"Y","cmRail":"Y","loWharves":"Y","loAnchor":"Y","loMedMoor":"U","loBeachMoor":"U","loIceMoor":"U","medFacilities":"Y","garbageDisposal":"U","degauss":"U","dirtyBallast":"N","crFixed":"Y","crMobile":"Y","crFloating":"U","lifts100":"U","lifts50":"U","lifts25":"U","lifts0":"Y","srLongshore":"U","srElectrical":"Y","srSteam":"U","srNavigEquip":"Y","srElectRepair":"Y","suProvisions":"Y","suWater":"Y","suFuel":"Y","suDiesel":"Y","suDeck":"N","suEngine":"Y","repairCode":"D","drydock":"U","railway":"U","qtSanitation":"U","suAviationFuel":"U","harborUse":"UNK","ukcMgmtSystem":"U","portSecurity":"U","etaMessage":"Y","searchAndRescue":"U","tss":"U","vts":"U","cht":"U","globalId":"{BA64EA55-5E40-48E9-814A-15BD8EE4E641}","loRoro":"U","loSolidBulk":"U","loContainer":"U","loBreakBulk":"U","loOilTerm":"U","loLongTerm":"U","loOther":"U","loDangCargo":"U","loLiquidBulk":"U","srIceBreaking":"U","srDiving":"U","cranesContainer":"U","unloCode":"MC MON","dnc":"a0838960, coa08k, gen08a, h0839025","s121WaterBody":"","s57Enc":null,"s101Enc":"","dodWaterBody":"Mediterranean Sea; North Atlantic Ocean","alternateName":null,"entranceWidth":null,"lngTerminalDepth":null,"offMaxVesselLength":null,"offMaxVesselBeam":null,"offMaxVesselDraft":null,"ycoord":43.73333300000007,"xcoord":7.416667000000075},"geometry":{"type":"Point","coordinates":[7.416667,43.733333]}}]}