{"type":"FeatureCollection","features":[{"id":"9467F7D1-0E85-4556-AD32-82877FA42181","type":"Feature","properties":{"portNumber":47220,"portName":"Victoria","regionNumber":47210,"regionName":"SEYCHELLES","countryCode":"SC","countryName":"Seychelles","latitude":"4°37'00\"S","longitude":"55°27'00\"E","publicationNumber":"Sailing Directions Pub. 171 (Enroute) - East Africa and the South Indian Ocean","chartNumber":"61542","navArea":"VIII","harborSize":"V","harborType":"CN","shelter":"F","erTide":"N","erSwell":"Y","erIce":"N","erOther":"Y","overheadLimits":"Y","chDepth":"2","anDepth":"14","cpDepth":"9","otDepth":"6","tide":2,"maxVesselLength":null,"maxVesselBeam":null,"maxVesselDraft":null,"goodHoldingGround":"Y","turningArea":"Y","firstPortOfEntry":"Y","usRep":"N","ptCompulsory":"Y","ptAvailable":null,"ptLocalAssist":null,"ptAdvisable":"Y","tugsSalvage":"U","tugsAssist":"Y","qtPratique":"Y","qtOther":"U","cmTelephone":"Y","cmTelegraph":"Y","cmRadio":"Y","cmRadioTel":"Y","cmAir":"Y","cmRail":"U","loWharves":"Y","loAnchor":"Y","loMedMoor":"U","loBeachMoor":"Y","loIceMoor":"U","medFacilities":"Y","garbageDisposal":"Y","degauss":"U","dirtyBallast":"N","crFixed":"Y","crMobile":"U","crFloating":"U","lifts100":"U","lifts50":"Y","lifts25":"Y","lifts0":"Y","srLongshore":"Y","srElectrical":"Y","srSteam":"U","srNavigEquip":"U","srElectRepair":"U","suProvisions":"U","suWater":"Y","suFuel":"Y","suDiesel":"Y","suDeck":"Y","suEngine":"Y","repairCode":"N","drydock":"U","railway":"U","qtSanitation":"Y","suAviationFuel":"U","harborUse":"UNK","ukcMgmtSystem":"U","portSecurity":"U","etaMessage":"Y","searchAndRescue":"U","tss":"U","vts":"U","cht":"U","globalId":"{9467F7D1-0E85-4556-AD32-82877FA42181}","loRoro":"U","loSolidBulk":"U","loContainer":"U","loBreakBulk":"U","loOilTerm":"U","loLongTerm":"U","loOther":"U","loDangCargo":"U","loLiquidBulk":"U","srIceBreaking":"U","srDiving":"U","cranesContainer":"U","unloCode":"SC POV","dnc":"coa02e, gen02a, h0247220","s121WaterBody":"","s57Enc":null,"s101Enc":"","dodWaterBody":"Indian Ocean","alternateName":"Mahe; Port Victoria","entranceWidth":null,"lngTerminalDepth":null,"offMaxVesselLength":null,"offMaxVesselBeam":null,"offMaxVesselDraft":null,"ycoord":-4.61666699999995,"xcoord":55.450000000000045},"geometry":{"type":"Point","coordinates":[55.45,-4.616667]}}]}