{"type":"FeatureCollection","features":[{"id":"B18A8451-C800-4C13-8AB7-63B0824EF736","type":"Feature","properties":{"portNumber":11372,"portName":"Coles Bay Oil Terminal","regionNumber":11355,"regionName":"ST MARTIN","countryCode":"SX","countryName":"Sint Maarten","latitude":"18°01'00\"N","longitude":"63°05'00\"W","publicationNumber":"Sailing Directions Pub. 147 (Enroute) - Caribbean Sea - Volume I","chartNumber":"25613","navArea":"IV","harborSize":"S","harborType":"OR","shelter":"F","erTide":"N","erSwell":"N","erIce":"N","erOther":"Y","overheadLimits":"N","chDepth":null,"anDepth":"11","cpDepth":null,"otDepth":"9","tide":1,"maxVesselLength":null,"maxVesselBeam":null,"maxVesselDraft":null,"goodHoldingGround":"U","turningArea":"Y","firstPortOfEntry":"N","usRep":"N","ptCompulsory":"N","ptAvailable":null,"ptLocalAssist":null,"ptAdvisable":"Y","tugsSalvage":"U","tugsAssist":"U","qtPratique":"U","qtOther":"U","cmTelephone":"U","cmTelegraph":"U","cmRadio":"Y","cmRadioTel":"Y","cmAir":"Y","cmRail":"U","loWharves":"Y","loAnchor":"U","loMedMoor":"U","loBeachMoor":"U","loIceMoor":"U","medFacilities":"Y","garbageDisposal":"N","degauss":"U","dirtyBallast":"N","crFixed":"U","crMobile":"U","crFloating":"U","lifts100":"U","lifts50":"U","lifts25":"U","lifts0":"U","srLongshore":"U","srElectrical":"U","srSteam":"U","srNavigEquip":"U","srElectRepair":"U","suProvisions":"U","suWater":"N","suFuel":"U","suDiesel":"U","suDeck":"U","suEngine":"U","repairCode":"N","drydock":"U","railway":"U","qtSanitation":"U","suAviationFuel":"U","harborUse":"UNK","ukcMgmtSystem":"U","portSecurity":"U","etaMessage":"U","searchAndRescue":"U","tss":"U","vts":"U","cht":"U","globalId":"{B18A8451-C800-4C13-8AB7-63B0824EF736}","loRoro":"U","loSolidBulk":"U","loContainer":"U","loBreakBulk":"U","loOilTerm":"U","loLongTerm":"U","loOther":"U","loDangCargo":"U","loLiquidBulk":"U","srIceBreaking":"U","srDiving":"U","cranesContainer":"U","unloCode":null,"dnc":"a1611370, coa16b, gen16, h1611370","s121WaterBody":"","s57Enc":null,"s101Enc":"","dodWaterBody":"Caribbean Sea; North Atlantic Ocean","alternateName":null,"entranceWidth":null,"lngTerminalDepth":null,"offMaxVesselLength":null,"offMaxVesselBeam":null,"offMaxVesselDraft":null,"ycoord":18.01666700000004,"xcoord":-63.08333299999998},"geometry":{"type":"Point","coordinates":[-63.083333,18.016667]}}]}