{"type":"FeatureCollection","features":[{"id":"E1B53833-F829-4802-994D-E56301E392E3","type":"Feature","properties":{"portNumber":51440,"portName":"Dili","regionNumber":51430,"regionName":"EAST TIMOR","countryCode":"TL","countryName":"Timor-Leste","latitude":"8°32'00\"S","longitude":"125°35'00\"E","publicationNumber":"Sailing Directions Pub. 163 (Enroute) - Borneo Jawa Sulawesi and Nusa Tenggara","chartNumber":"73082","navArea":"XI","harborSize":"S","harborType":"CN","shelter":"G","erTide":"U","erSwell":"U","erIce":"U","erOther":"U","overheadLimits":"U","chDepth":"23","anDepth":"23","cpDepth":"6","otDepth":null,"tide":5,"maxVesselLength":null,"maxVesselBeam":null,"maxVesselDraft":null,"goodHoldingGround":"U","turningArea":"U","firstPortOfEntry":"Y","usRep":"U","ptCompulsory":"N","ptAvailable":null,"ptLocalAssist":null,"ptAdvisable":"Y","tugsSalvage":"N","tugsAssist":"N","qtPratique":"Y","qtOther":"U","cmTelephone":"Y","cmTelegraph":"Y","cmRadio":"Y","cmRadioTel":"Y","cmAir":"U","cmRail":"U","loWharves":"U","loAnchor":"Y","loMedMoor":"U","loBeachMoor":"U","loIceMoor":"U","medFacilities":"Y","garbageDisposal":"Y","degauss":"U","dirtyBallast":"U","crFixed":"U","crMobile":"Y","crFloating":"U","lifts100":"U","lifts50":"U","lifts25":"U","lifts0":"Y","srLongshore":"Y","srElectrical":"U","srSteam":"U","srNavigEquip":"U","srElectRepair":"U","suProvisions":"Y","suWater":"Y","suFuel":"Y","suDiesel":"U","suDeck":"U","suEngine":"U","repairCode":"U","drydock":"U","railway":"U","qtSanitation":"Y","suAviationFuel":"U","harborUse":"UNK","ukcMgmtSystem":"U","portSecurity":"U","etaMessage":"Y","searchAndRescue":"U","tss":"U","vts":"U","cht":"U","globalId":"{E1B53833-F829-4802-994D-E56301E392E3}","loRoro":"U","loSolidBulk":"U","loContainer":"U","loBreakBulk":"U","loOilTerm":"U","loLongTerm":"U","loOther":"U","loDangCargo":"U","loLiquidBulk":"U","srIceBreaking":"U","srDiving":"U","cranesContainer":"U","unloCode":"TL DIL","dnc":"coa04g, gen04c, h0451390","s121WaterBody":"","s57Enc":null,"s101Enc":"","dodWaterBody":"Banda Sea; South Pacific Ocean","alternateName":null,"entranceWidth":null,"lngTerminalDepth":null,"offMaxVesselLength":null,"offMaxVesselBeam":null,"offMaxVesselDraft":null,"ycoord":-8.53333299999997,"xcoord":125.58333300000004},"geometry":{"type":"Point","coordinates":[125.583333,-8.533333]}}]}