{"type":"FeatureCollection","features":[{"id":"B900590D-AFF4-4C93-B06C-E0B67F15DBF9","type":"Feature","properties":{"portNumber":55650,"portName":"Mata-Utu","regionNumber":55640,"regionName":"ILES WALLIS","countryCode":"WF","countryName":"Wallis And Futuna","latitude":"13°17'00\"S","longitude":"176°08'00\"W","publicationNumber":"Sailing Directions Pub. 126 (Enroute) - Pacific Islands","chartNumber":"83495","navArea":"XIV","harborSize":"V","harborType":"OR","shelter":"F","erTide":"N","erSwell":"N","erIce":"N","erOther":"Y","overheadLimits":"N","chDepth":"6","anDepth":"11","cpDepth":"3","otDepth":null,"tide":4,"maxVesselLength":null,"maxVesselBeam":null,"maxVesselDraft":null,"goodHoldingGround":"Y","turningArea":"Y","firstPortOfEntry":"U","usRep":"U","ptCompulsory":"U","ptAvailable":null,"ptLocalAssist":null,"ptAdvisable":"U","tugsSalvage":"U","tugsAssist":"U","qtPratique":"U","qtOther":"U","cmTelephone":"U","cmTelegraph":"U","cmRadio":"Y","cmRadioTel":"U","cmAir":"U","cmRail":"U","loWharves":"U","loAnchor":"Y","loMedMoor":"U","loBeachMoor":"U","loIceMoor":"U","medFacilities":"Y","garbageDisposal":"U","degauss":"U","dirtyBallast":"U","crFixed":"N","crMobile":"U","crFloating":"U","lifts100":"U","lifts50":"U","lifts25":"U","lifts0":"U","srLongshore":"U","srElectrical":"U","srSteam":"U","srNavigEquip":"U","srElectRepair":"U","suProvisions":"Y","suWater":"Y","suFuel":"U","suDiesel":"U","suDeck":"U","suEngine":"U","repairCode":"D","drydock":"U","railway":"U","qtSanitation":"U","suAviationFuel":"U","harborUse":"UNK","ukcMgmtSystem":"U","portSecurity":"U","etaMessage":"U","searchAndRescue":"U","tss":"U","vts":"U","cht":"U","globalId":"{B900590D-AFF4-4C93-B06C-E0B67F15DBF9}","loRoro":"U","loSolidBulk":"U","loContainer":"U","loBreakBulk":"U","loOilTerm":"U","loLongTerm":"U","loOther":"U","loDangCargo":"U","loLiquidBulk":"U","srIceBreaking":"U","srDiving":"U","cranesContainer":"U","unloCode":"WF MAU","dnc":"gen06c","s121WaterBody":"","s57Enc":null,"s101Enc":"","dodWaterBody":"South Pacific Ocean","alternateName":null,"entranceWidth":null,"lngTerminalDepth":null,"offMaxVesselLength":null,"offMaxVesselBeam":null,"offMaxVesselDraft":null,"ycoord":-13.28333299999997,"xcoord":-176.13333299999996},"geometry":{"type":"Point","coordinates":[-176.133333,-13.283333]}}]}