{"type":"FeatureCollection","features":[{"id":"302308","type":"Feature","properties":{"ident":"TBPO","type":"heliport","name":"Bridgetown Heliport","continent":"NA","iso_country":"BB","iso_region":"BB-08","scheduled_service":"no","icao_code":"TBPO","gps_code":"TBPO","wikipedia_link":"https://en.wikipedia.org/wiki/Bridgetown_Heliport"},"geometry":{"type":"Point","coordinates":[-59.618611,13.095833]}},{"id":"6360","type":"Feature","properties":{"ident":"TBPB","type":"large_airport","name":"Grantley Adams International Airport","elevation_ft":"169","continent":"NA","iso_country":"BB","iso_region":"BB-01","municipality":"Bridgetown","scheduled_service":"yes","icao_code":"TBPB","iata_code":"BGI","gps_code":"TBPB","home_link":"http://www.gaia.bb/content/about-gaia-inc","wikipedia_link":"https://en.wikipedia.org/wiki/Grantley_Adams_International_Airport","keywords":"Seawell"},"geometry":{"type":"Point","coordinates":[-59.491034,13.074667]}}]}