{"type":"FeatureCollection","features":[{"id":"302308","type":"Feature","properties":{"ident":"TBPO","type":"heliport","name":"Bridgetown Heliport","continent":"NA","iso_country":"BB","iso_region":"BB-08","scheduled_service":"no","gps_code":"TBPO","wikipedia_link":"https://en.wikipedia.org/wiki/Bridgetown_Heliport"},"geometry":{"type":"Point","coordinates":[-59.618611,13.095833]}},{"id":"515670","type":"Feature","properties":{"ident":"BB-0001","type":"large_airport","name":"Delete spam","continent":"NA","iso_country":"BB","iso_region":"BB-02","scheduled_service":"no","keywords":"kaya88 login"},"geometry":{"type":"Point","coordinates":[-0.07,0.03]}},{"id":"6360","type":"Feature","properties":{"ident":"TBPB","type":"medium_airport","name":"Grantley Adams International Airport","elevation_ft":"169","continent":"NA","iso_country":"BB","iso_region":"BB-01","municipality":"Bridgetown","scheduled_service":"yes","gps_code":"TBPB","iata_code":"BGI","home_link":"http://www.gaia.bb/content/about-gaia-inc","wikipedia_link":"https://en.wikipedia.org/wiki/Grantley_Adams_International_Airport","keywords":"Seawell"},"geometry":{"type":"Point","coordinates":[-59.4925,13.0746]}}]}