{"type":"FeatureCollection","features":[{"id":"27122","type":"Feature","properties":{"ident":"YPXM","type":"medium_airport","name":"Christmas Island Airport","elevation_ft":"916","continent":"AS","iso_country":"CX","iso_region":"CX-U-A","municipality":"Flying Fish Cove","scheduled_service":"yes","gps_code":"YPXM","iata_code":"XCH","home_link":"http://www.christmasislandairport.com/","wikipedia_link":"https://en.wikipedia.org/wiki/Christmas_Island_Airport"},"geometry":{"type":"Point","coordinates":[105.690931,-10.449382]}}]}