{"type":"FeatureCollection","features":[{"id":"27122","type":"Feature","properties":{"ident":"YPXM","type":"large_airport","name":"Christmas Island International Airport","elevation_ft":"916","continent":"AS","iso_country":"CX","iso_region":"CX-U-A","municipality":"Flying Fish Cove","scheduled_service":"yes","icao_code":"YPXM","iata_code":"XCH","gps_code":"YPXM","home_link":"http://www.christmasislandairport.com/","wikipedia_link":"https://en.wikipedia.org/wiki/Christmas_Island_Airport"},"geometry":{"type":"Point","coordinates":[105.6911,-10.450387]}}]}