{"type":"FeatureCollection","features":[{"id":"2424","type":"Feature","properties":{"ident":"EGJA","type":"medium_airport","name":"Alderney Airport","elevation_ft":"290","continent":"EU","iso_country":"GG","iso_region":"GG-U-A","municipality":"Saint Anne","scheduled_service":"yes","gps_code":"EGJA","iata_code":"ACI","wikipedia_link":"https://en.wikipedia.org/wiki/Alderney_Airport","keywords":"The Blaye, Channel Islands"},"geometry":{"type":"Point","coordinates":[-2.21472,49.706104]}},{"id":"2425","type":"Feature","properties":{"ident":"EGJB","type":"medium_airport","name":"Guernsey Airport","elevation_ft":"336","continent":"EU","iso_country":"GG","iso_region":"GG-U-A","municipality":"Saint Peter Port","scheduled_service":"yes","gps_code":"EGJB","iata_code":"GCI","wikipedia_link":"https://en.wikipedia.org/wiki/Guernsey_Airport","keywords":"Channel Islands"},"geometry":{"type":"Point","coordinates":[-2.60197,49.435001]}}]}