{"type":"FeatureCollection","features":[{"id":"2424","type":"Feature","properties":{"ident":"EGJA","type":"medium_airport","name":"Alderney Airport","elevation_ft":"290","continent":"EU","iso_country":"GG","iso_region":"GG-A","municipality":"Saint Anne","scheduled_service":"yes","icao_code":"EGJA","iata_code":"ACI","gps_code":"EGJA","wikipedia_link":"https://en.wikipedia.org/wiki/Alderney_Airport","keywords":"The Blaye, Channel Islands"},"geometry":{"type":"Point","coordinates":[-2.21472,49.706104]}},{"id":"2425","type":"Feature","properties":{"ident":"EGJB","type":"medium_airport","name":"Guernsey Airport","elevation_ft":"336","continent":"EU","iso_country":"GG","iso_region":"GG-G","municipality":"Saint Peter Port","scheduled_service":"yes","icao_code":"EGJB","iata_code":"GCI","gps_code":"EGJB","wikipedia_link":"https://en.wikipedia.org/wiki/Guernsey_Airport","keywords":"Channel Islands"},"geometry":{"type":"Point","coordinates":[-2.60197,49.435001]}},{"id":"534991","type":"Feature","properties":{"ident":"GG-0002","type":"heliport","name":"Jethou Private Heliport","elevation_ft":"210","continent":"EU","iso_country":"GG","iso_region":"GG-G","municipality":"Jethou","scheduled_service":"no","keywords":"Cannon Field"},"geometry":{"type":"Point","coordinates":[-2.46263,49.45857]}}]}