{"type":"FeatureCollection","features":[{"id":"2426","type":"Feature","properties":{"ident":"EGJJ","type":"medium_airport","name":"Jersey Airport","elevation_ft":"277","continent":"EU","iso_country":"JE","iso_region":"JE-U-A","municipality":"St. Peter","scheduled_service":"yes","icao_code":"EGJJ","iata_code":"JER","gps_code":"EGJJ","home_link":"http://www.jerseyairport.com/","wikipedia_link":"https://en.wikipedia.org/wiki/Jersey_Airport","keywords":"Channel Islands"},"geometry":{"type":"Point","coordinates":[-2.19551,49.207901]}}]}