{"type":"FeatureCollection","features":[{"id":"6388","type":"Feature","properties":{"ident":"TLPC","type":"medium_airport","name":"George F. L. Charles Airport","elevation_ft":"22","continent":"NA","iso_country":"LC","iso_region":"LC-02","municipality":"Castries","scheduled_service":"yes","gps_code":"TLPC","iata_code":"SLU","home_link":"http://www.slaspa.com/contentPages/view/george-f-l-charles-airport","wikipedia_link":"https://en.wikipedia.org/wiki/George_F._L._Charles_Airport","keywords":"Vigie Airport"},"geometry":{"type":"Point","coordinates":[-60.992901,14.0202]}},{"id":"6389","type":"Feature","properties":{"ident":"TLPL","type":"large_airport","name":"Hewanorra International Airport","elevation_ft":"14","continent":"NA","iso_country":"LC","iso_region":"LC-11","municipality":"Vieux Fort","scheduled_service":"yes","gps_code":"TLPL","iata_code":"UVF","home_link":"http://www.slaspa.com/contentPages/view/hewanorra-international-airport","wikipedia_link":"https://en.wikipedia.org/wiki/Hewanorra_International_Airport"},"geometry":{"type":"Point","coordinates":[-60.952599,13.7332]}}]}