{"type":"FeatureCollection","features":[{"id":"43074","type":"Feature","properties":{"ident":"TRPG","type":"large_airport","name":"John A. Osborne Airport","elevation_ft":"550","continent":"NA","iso_country":"MS","iso_region":"MS-SP","municipality":"Gerald's Park","scheduled_service":"yes","icao_code":"TRPG","iata_code":"MNI","gps_code":"TRPG","wikipedia_link":"https://en.wikipedia.org/wiki/John_A._Osborne_Airport","keywords":"Gerald's Airport, Brades"},"geometry":{"type":"Point","coordinates":[-62.193204,16.791835]}}]}