{"type":"FeatureCollection","features":[{"id":"30608","type":"Feature","properties":{"ident":"NSAU","type":"small_airport","name":"Asau Airport","continent":"OC","iso_country":"WS","iso_region":"WS-VS","municipality":"Asau","scheduled_service":"yes","gps_code":"NSAU","iata_code":"AAU","wikipedia_link":"https://en.wikipedia.org/wiki/Asau_Airport"},"geometry":{"type":"Point","coordinates":[-172.627888,-13.505132]}},{"id":"31127","type":"Feature","properties":{"ident":"NSFI","type":"small_airport","name":"Fagali'i Airport","elevation_ft":"131","continent":"OC","iso_country":"WS","iso_region":"WS-TU","municipality":"Apia","scheduled_service":"no","gps_code":"NSFI","iata_code":"FGI","wikipedia_link":"https://en.wikipedia.org/wiki/Fagali'i_Airport"},"geometry":{"type":"Point","coordinates":[-171.739866,-13.849167]}},{"id":"4976","type":"Feature","properties":{"ident":"NSFA","type":"medium_airport","name":"Faleolo International Airport","elevation_ft":"58","continent":"OC","iso_country":"WS","iso_region":"WS-AA","municipality":"Apia","scheduled_service":"yes","gps_code":"NSFA","iata_code":"APW","wikipedia_link":"https://en.wikipedia.org/wiki/Faleolo_International_Airport"},"geometry":{"type":"Point","coordinates":[-172.007996,-13.83]}},{"id":"35173","type":"Feature","properties":{"ident":"NSMA","type":"small_airport","name":"Maota Airport","continent":"OC","iso_country":"WS","iso_region":"WS-PA","municipality":"Maota","scheduled_service":"yes","gps_code":"NSMA","iata_code":"MXS","wikipedia_link":"https://en.wikipedia.org/wiki/Maota_Airport","keywords":"Savaii Island"},"geometry":{"type":"Point","coordinates":[-172.257996,-13.7423]}}]}